pysparklogger/__init__.py
pysparklogger/logger.py
pysparklogger-0.1.dist-info/LICENSE
pysparklogger-0.1.dist-info/METADATA
pysparklogger-0.1.dist-info/WHEEL
pysparklogger-0.1.dist-info/top_level.txt
pysparklogger-0.1.dist-info/RECORD
