Metadata-Version: 2.1
Name: pysparklogger
Version: 0.1
Summary: Logger for pyspark
Home-page: https://pip.pypa.io/
Author: arunenquero
Author-email: arunkumar.rn@enquero.com
License: MIT
Platform: UNKNOWN
